{
  "slug": "defra-cattle-tracing-system-movements",
  "page-type": "dashboard",
  "dashboard-type": "transaction",
  "strapline": "Dashboard",
  "description": "The Cattle Tracing System (CTS) is used by the British Cattle Movement Service to record the births, movements and deaths of cattle to help disease control. ",
  "title": "Cattle Tracing System: movements",
  "department": {
    "title": "Department for Environment, Food and Rural Affairs"
  },
  "agency": {
    "title": "Rural Payments Agency"
  },
  "relatedPages": {
    "transaction": {
      "title": "Cattle Tracing System: movements",
      "url": "https://www.gov.uk/cattle-tracing-online"
    }
  },
  "description-extra": "The CTS lets users see:\n\n- details of passport applications and movements\n- all births, movements and deaths reported in the last 6 months\n- calving histories for their animals\n\nUsers can send information to the British Cattle Movement Service to help resolve problems.\n\n",
  "customer-type": "Business",
  "business-model": "Fiscal",
  "costs": "The total costs for this service have been aligned with the Single Payment Scheme methodology. For the 2010/11 and 2011/12 financial years the equivalent costs were £1.31 and £1.30 respectively.",
  "modules": [
    {
      "slug": "transactions-per-year",
      "module-type": "kpi",
      "title": "Transactions per year",
      "data-group": "transactions-explorer",
      "data-type": "spreadsheet",
      "classes": "cols3",
      "query-params": {
        "filter_by": [
          "service_id:defra-cattle-tracing-system-movements",
          "type:seasonally-adjusted"
        ],
        "sort_by": "_timestamp:descending"
      },
      "value-attribute": "number_of_transactions",
      "format": {
        "type": "number",
        "magnitude": true,
        "sigfigs": 3
      }
    },
    {
      "slug": "total-cost",
      "module-type": "kpi",
      "title": "Total cost",
      "data-group": "transactions-explorer",
      "data-type": "spreadsheet",
      "classes": "cols3",
      "query-params": {
        "filter_by": [
          "service_id:defra-cattle-tracing-system-movements",
          "type:seasonally-adjusted"
        ],
        "sort_by": "_timestamp:descending"
      },
      "value-attribute": "total_cost",
      "format": {
        "type": "currency",
        "magnitude": true,
        "sigfigs": 3
      }
    },
    {
      "slug": "cost-per-transaction",
      "module-type": "kpi",
      "title": "Cost per transaction",
      "data-group": "transactions-explorer",
      "data-type": "spreadsheet",
      "classes": "cols3",
      "query-params": {
        "filter_by": [
          "service_id:defra-cattle-tracing-system-movements",
          "type:seasonally-adjusted"
        ],
        "sort_by": "_timestamp:descending"
      },
      "value-attribute": "cost_per_transaction",
      "format": {
        "type": "currency",
        "pence": true
      }
    },
    {
      "slug": "transactions-per-quarter",
      "module-type": "bar_chart_with_number",
      "title": "Transactions per quarter",
      "description": "Total number of transactions each quarter",
      "data-group": "transactions-explorer",
      "data-type": "spreadsheet",
      "value-attribute": "number_of_transactions",
      "axis-period": "quarter",
      "query-params": {
        "filter_by": [
          "service_id:defra-cattle-tracing-system-movements",
          "type:quarterly"
        ]
      }
    },
    {
      "slug": "digital-take-up-per-quater",
      "module-type": "bar_chart_with_number",
      "title": "Digital Take-up",
      "description": "Digital take-up for each quater",
      "data-group": "transactions-explorer",
      "data-type": "spreadsheet",
      "value-attribute": "digital_takeup",
      "axis-period": "quarter",
      "format": {
        "type": "percentage"
      },
      "query-params": {
        "filter_by": [
          "service_id:defra-cattle-tracing-system-movements",
          "type:quarterly"
        ]
      }
    }
  ]
}