{
  "slug": "dft-report-change-of-ownership-of-vehicle",
  "page-type": "dashboard",
  "dashboard-type": "high-volume-transaction",
  "strapline": "Dashboard",
  "description": "Telling DVLA that a vehicle has changed owner.",
  "title": "Vehicle registration: changes of ownership",
  "department": {
    "title": "Department for Transport"
  },
  "agency": {
    "title": "Driver and Vehicle Licensing Agency"
  },
  "relatedPages": {
    "transaction": {
      "title": "Vehicle registration: changes of ownership",
      "url": "https://www.gov.uk/notifying-dvla-if-you-sell-your-vehicle"
    }
  },
  "customer-type": "Citizen",
  "business-model": "Cost recovery",
  "costs": "The volume and cost data presented here is subject to change as the method of calculation is refined. Until it has been through a formal assurance process, care should be taken in using the data to support analysis of DVLA business.",
  "modules": [
    {
      "slug": "transactions-per-year",
      "module-type": "kpi",
      "title": "Transactions per year",
      "data-group": "transactional-services",
      "data-type": "summaries",
      "classes": "cols3",
      "query-params": {
        "filter_by": [
          "service_id:dft-report-change-of-ownership-of-vehicle",
          "type:seasonally-adjusted"
        ],
        "sort_by": "_timestamp:descending"
      },
      "value-attribute": "number_of_transactions",
      "format": {
        "type": "number",
        "magnitude": true,
        "sigfigs": 3
      }
    },
    {
      "slug": "total-cost",
      "module-type": "kpi",
      "title": "Total cost",
      "data-group": "transactional-services",
      "data-type": "summaries",
      "classes": "cols3",
      "query-params": {
        "filter_by": [
          "service_id:dft-report-change-of-ownership-of-vehicle",
          "type:seasonally-adjusted"
        ],
        "sort_by": "_timestamp:descending"
      },
      "value-attribute": "total_cost",
      "format": {
        "type": "currency",
        "magnitude": true,
        "sigfigs": 3
      }
    },
    {
      "slug": "cost-per-transaction",
      "module-type": "kpi",
      "title": "Cost per transaction",
      "data-group": "transactional-services",
      "data-type": "summaries",
      "classes": "cols3",
      "query-params": {
        "filter_by": [
          "service_id:dft-report-change-of-ownership-of-vehicle",
          "type:seasonally-adjusted"
        ],
        "sort_by": "_timestamp:descending"
      },
      "value-attribute": "cost_per_transaction",
      "format": {
        "type": "currency",
        "pence": true
      }
    },
    {
      "slug": "transactions-per-quarter",
      "module-type": "bar_chart_with_number",
      "title": "Transactions per quarter",
      "description": "Total number of transactions each quarter",
      "data-group": "transactional-services",
      "data-type": "summaries",
      "value-attribute": "number_of_transactions",
      "axis-period": "quarter",
      "query-params": {
        "filter_by": [
          "service_id:dft-report-change-of-ownership-of-vehicle",
          "type:quarterly"
        ]
      }
    },
    {
      "slug": "digital-take-up-per-quater",
      "module-type": "bar_chart_with_number",
      "title": "Digital take-up",
      "description": "Digital take-up for each quater",
      "data-group": "transactional-services",
      "data-type": "summaries",
      "value-attribute": "digital_takeup",
      "axis-period": "quarter",
      "format": {
        "type": "percentage"
      },
      "query-params": {
        "filter_by": [
          "service_id:dft-report-change-of-ownership-of-vehicle",
          "type:quarterly"
        ]
      }
    }
  ]
}